reperiods/__init__.py
reperiods/datasets.py
reperiods/export.py
reperiods/plot.py
reperiods/representative_periods.py
reperiods/temporal_data.py
reperiods/utils.py
reperiods/find_RP/kmedoids.py
reperiods/find_RP/poncelet.py
reperiods/find_RP/random.py
reperiods-2.0.1.dist-info/licenses/LICENSE
reperiods-2.0.1.dist-info/METADATA
reperiods-2.0.1.dist-info/WHEEL
reperiods-2.0.1.dist-info/top_level.txt
reperiods-2.0.1.dist-info/RECORD
