Metadata-Version: 2.4
Name: reperiods
Version: 2.0.1
Summary: Add your description here
Requires-Python: <3.12,>=3.10
License-File: LICENSE
Requires-Dist: pandas>=2.2.3
Requires-Dist: plotly>=6.1.2
Requires-Dist: pulp>=3.2.1
Requires-Dist: scikit-learn>=1.6.1
Provides-Extra: kmedoids
Requires-Dist: scikit-learn-extra>=0.3.0; extra == "kmedoids"
Requires-Dist: numpy<2.0.0; extra == "kmedoids"
Provides-Extra: notebook
Requires-Dist: ipykernel>=6.29.5; extra == "notebook"
Requires-Dist: nbconvert>=7.16.6; extra == "notebook"
Provides-Extra: dev
Requires-Dist: nbmake>=1.5.5; extra == "dev"
Requires-Dist: nbsphinx>=0.9.7; extra == "dev"
Requires-Dist: pytest>=8.3.5; extra == "dev"
Requires-Dist: pytest-cov>=6.1.1; extra == "dev"
Requires-Dist: ruff>=0.11.12; extra == "dev"
Requires-Dist: sphinx>=8.1.3; extra == "dev"
Requires-Dist: sphinx-rtd-theme>=3.0.2; extra == "dev"
Dynamic: license-file
